async_logger/__init__.py
async_logger/logger.py
async_logger/logger_config.py
async_logger-0.2.dist-info/METADATA
async_logger-0.2.dist-info/WHEEL
async_logger-0.2.dist-info/top_level.txt
async_logger-0.2.dist-info/RECORD
