Metadata-Version: 2.1
Name: async_logger
Version: 0.2
Summary: A custom asynchronous logging library with Elasticsearch integration.
Home-page: https://github.com/nimamiri9248/async_elastic_logger
Author: Nima Miri
Author-email: nimamiri9248@gmail.com
License: MIT
Classifier: Intended Audience :: Developers
Classifier: License :: OSI Approved :: MIT License
Classifier: Programming Language :: Python :: 3.10
Classifier: Programming Language :: Python :: 3.11
Classifier: Programming Language :: Python :: 3.12
Classifier: Topic :: Software Development :: Libraries :: Python Modules
Classifier: Topic :: System :: Logging
Requires-Dist: pydantic
Requires-Dist: pydantic-settings
Requires-Dist: elasticsearch[async]
